hall/__init__.py
hall/_core.py
hall/_event.py
hall/analysis.py
hall/backend.py
hall/continuous.py
hall/discrete.py
hall/numbers.py
hall/stats.py
hall-0.1.13.dist-info/entry_points.txt
hall-0.1.13.dist-info/LICENSE
hall-0.1.13.dist-info/WHEEL
hall-0.1.13.dist-info/METADATA
hall-0.1.13.dist-info/RECORD
